mettle/__init__.py
mettle/__main__.py
mettle/braze/__init__.py
mettle/braze/bool_list.py
mettle/braze/char_list.py
mettle/braze/client.py
mettle/braze/date_list.py
mettle/braze/datetime_list.py
mettle/braze/double_list.py
mettle/braze/float_list.py
mettle/braze/guid_list.py
mettle/braze/iclient_marshaler.py
mettle/braze/int16_list.py
mettle/braze/int32_list.py
mettle/braze/int64_list.py
mettle/braze/int8_list.py
mettle/braze/iserver_interface.py
mettle/braze/iserver_marshaler.py
mettle/braze/itransport.py
mettle/braze/itransport_settings.py
mettle/braze/json_list.py
mettle/braze/memblock_list.py
mettle/braze/rdc.py
mettle/braze/rpc_header.py
mettle/braze/server.py
mettle/braze/server_multimarsh.py
mettle/braze/string_list.py
mettle/braze/time_list.py
mettle/braze/uint16_list.py
mettle/braze/uint32_list.py
mettle/braze/uint64_list.py
mettle/braze/uint8_list.py
mettle/braze/http/__init__.py
mettle/braze/http/http_header.py
mettle/braze/http/transport_client.py
mettle/braze/http/transport_client_settings.py
mettle/braze/http/transport_server.py
mettle/braze/http/transport_server_settings.py
mettle/braze/tcp/__init__.py
mettle/braze/tcp/socket_tcp.py
mettle/braze/tcp/socket_tcp_client.py
mettle/braze/tcp/socket_tcp_server.py
mettle/braze/tcp/tcp_header.py
mettle/braze/tcp/transport_client.py
mettle/braze/tcp/transport_client_settings.py
mettle/braze/tcp/transport_server.py
mettle/braze/tcp/transport_server_settings.py
mettle/db/__init__.py
mettle/db/db_lock.py
mettle/db/iaconnect.py
mettle/db/iconnect.py
mettle/db/iprimary_key.py
mettle/db/sqlvar.py
mettle/db/statement.py
mettle/db/encode_io_databases/__init__.py
mettle/db/encode_io_databases/aconnect.py
mettle/db/encode_io_databases/aconnect_postgres.py
mettle/db/encode_io_databases/statement.py
mettle/db/psycopg2/__init__.py
mettle/db/psycopg2/connect.py
mettle/db/psycopg2/statement.py
mettle/db/psycopg3/__init__.py
mettle/db/psycopg3/aconnect.py
mettle/db/psycopg3/astatement.py
mettle/db/psycopg3/connect.py
bitsmiths_mettle-2.2.9.dist-info/LICENCE
bitsmiths_mettle-2.2.9.dist-info/METADATA
bitsmiths_mettle-2.2.9.dist-info/WHEEL
bitsmiths_mettle-2.2.9.dist-info/entry_points.txt
bitsmiths_mettle-2.2.9.dist-info/top_level.txt
bitsmiths_mettle-2.2.9.dist-info/RECORD
