Metadata-Version: 2.1
Name: bitsmiths-mettle
Version: 2.2.9
Summary: A three tier systems code generator that targets serveral databases and languages
Home-page: https://bitbucket.org/bitsmiths_za/mettle.git
Author: Nicolas Milicevic, Steven van Niekerk, Darrly Daniels
Author-email: nicolas@bitsmiths.co.za, steven@bitsmiths.co.za, darryl@bitsmiths.co.za
License: MIT
Project-URL: Source, https://bitbucket.org/bitsmiths_za/mettle.git
Keywords: generators,libraries
Platform: unix
Platform: linux
Platform: osx
Platform: cygwin
Platform: win32
Classifier: Development Status :: 5 - Production/Stable
Classifier: Intended Audience :: Developers
Classifier: License :: OSI Approved :: MIT License
Classifier: Operating System :: MacOS :: MacOS X
Classifier: Operating System :: POSIX
Classifier: Programming Language :: Python :: 3.10
Classifier: Programming Language :: Python :: 3.11
Classifier: Programming Language :: Python :: 3 :: Only
Classifier: Topic :: Software Development :: Libraries
Classifier: Topic :: Software Development :: Libraries :: Python Modules
Classifier: Topic :: Software Development :: Code Generators
Requires-Python: >=3.10
License-File: LICENCE
Requires-Dist: pyyaml (>=5.0.0)
Requires-Dist: sqlparse (>=0.4.1)
Requires-Dist: stringcase (>=1.2.0)
Provides-Extra: postgresql_async
Requires-Dist: databases[postgresql] (>=0.4.1) ; extra == 'postgresql_async'
Provides-Extra: postgresql_psycopg2
Requires-Dist: psycopg2 ; extra == 'postgresql_psycopg2'
Provides-Extra: postgresql_psycopg3
Requires-Dist: psycopg ; extra == 'postgresql_psycopg3'
Provides-Extra: sqlalchemy
Requires-Dist: sqlalchemy ; extra == 'sqlalchemy'
Requires-Dist: psycopg2 ; extra == 'sqlalchemy'
Requires-Dist: asyncpg (>=0.21.0) ; extra == 'sqlalchemy'
Provides-Extra: sqlite_async
Requires-Dist: databases[sqlite] (>=0.4.1) ; extra == 'sqlite_async'
